Metadata-Version: 2.1
Name: odoo13-addon-partner-identification-gln
Version: 13.0.1.0.1.dev3
Summary: This addon extends "Partner Identification Numbers" to provide a number category for GLN registration
Home-page: https://github.com/OCA/partner-contact
Author: Acsone S.A.,Odoo Community Association (OCA)
Author-email: support@odoo-community.org
License: AGPL-3
Platform: UNKNOWN
Classifier: Programming Language :: Python
Classifier: Framework :: Odoo
Classifier: Framework :: Odoo :: 13.0
Classifier: License :: OSI Approved :: GNU Affero General Public License v3
Requires-Python: >=3.5
Requires-Dist: odoo13-addon-partner-identification
Requires-Dist: odoo <13.1dev,>=13.0a
Requires-Dist: python-stdnum
